cedula_lib.cp312-win_amd64.pyd
cedula_lib-0.0.2.dist-info/METADATA
cedula_lib-0.0.2.dist-info/WHEEL
cedula_lib-0.0.2.dist-info/top_level.txt
cedula_lib-0.0.2.dist-info/RECORD
