Metadata-Version: 2.1
Name: cedula_lib
Version: 0.0.2
Summary: Módulo en C para formatear y consultar cédulas
